{
    "@odata.type": "#Volume.v1_10_2.Volume",
    "Id": "Secondary Storage",
    "Name": "Scratchpad Volume",
    "Status": {
        "State": "Enabled",
        "Health": "OK"
    },
    "Encrypted": false,
    "RAIDType": "RAID5",
    "CapacityBytes": 40532396646334460,
    "Identifiers": [
        {
            "DurableNameFormat": "UUID",
            "DurableName": "38f1818b-111e-463a-aa19-fa54f792e468"
        }
    ],
    "Links": {
        "Drives": [
            {
                "@odata.id": "/redfish/v1/Chassis/Tower/Drives/Disk-1-1"
            },
            {
                "@odata.id": "/redfish/v1/Chassis/Tower/Drives/Disk-1-2"
            },
            {
                "@odata.id": "/redfish/v1/Chassis/Tower/Drives/Disk-1-3"
            }
        ]
    },
    "@odata.id": "/redfish/v1/Systems/437XR1238R2/Storage/RAIDIntegrated/Volumes/Secondary",
    "@Redfish.Copyright": "Copyright 2014-2025 DMTF. For the full DMTF copyright policy, see http://www.dmtf.org/about/policies/copyright."
}