{
    "@odata.type": "#MemoryRegion.v1_0_3.MemoryRegion",
    "Id": "1",
    "Name": "Static Memory Region 1",
    "Description": "CXL Static Memory Region 1 of LD 1 in Device 1",
    "Status": {
        "State": "Enabled",
        "Health": "OK",
        "HealthRollup": "OK"
    },
    "RegionType": "Static",
    "RegionNumber": 0,
    "NonVolatileRegion": true,
    "RegionBaseOffsetMiB": 0,
    "RegionSizeMiB": 16384,
    "ShareableRegion": false,
    "SanitizeOnRelease": true,
    "BlockSizeMiB": 128,
    "ExtentsCount": 1,
    "MemoryExtents": [
        {
            "ExtentOffsetMiB": 0,
            "ExtentSizeMiB": 16384,
            "Tag": "User Defined Tag",
            "SequenceNumber": 0
        }
    ],
    "MemoryChunks": [
        {
            "ChunkOffsetMiB": 0,
            "ChunkLink": {
                "@odata.id": "/redfish/v1/Chassis/PooledCXLType3/MemoryDomains/1/MemoryChunks/1"
            }
        }
    ],
    "@odata.id": "/redfish/v1/Chassis/PooledCXLType3/PCIeDevices/1/CXLLogicalDevices/1/MemoryRegions/1",
    "@Redfish.Copyright": "Copyright 2014-2025 DMTF. For the full DMTF copyright policy, see http://www.dmtf.org/about/policies/copyright."
}