{
    "@odata.type": "#LeakDetection.v1_1_0.LeakDetection",
    "Id": "LeakDetection",
    "Name": "Leak Detection Systems",
    "Status": {
        "State": "Enabled",
        "Health": "OK",
        "Conditions": []
    },
    "LeakDetectorGroups": [
        {
            "GroupName": "Detectors under and around the CDU",
            "Status": {
                "Health": "OK"
            },
            "HumidityPercent": {
                "Reading": 45
            },
            "Detectors": [
                {
                    "DataSourceUri": "/redfish/v1/ThermalEquipment/CDUs/1/LeakDetection/LeakDetectors/Moisture",
                    "DeviceName": "Moisture-type Leak Detector",
                    "DetectorState": "OK"
                },
                {
                    "DeviceName": "Leak Detection Rope 1",
                    "DetectorState": "OK"
                },
                {
                    "DataSourceUri": "/redfish/v1/ThermalEquipment/CDUs/1/LeakDetection/LeakDetectors/Overflow",
                    "DeviceName": "Overflow Float Switch",
                    "DetectorState": "OK"
                }
            ]
        }
    ],
    "LeakDetectors": {
        "@odata.id": "/redfish/v1/ThermalEquipment/CDUs/1/LeakDetection/LeakDetectors"
    },
    "@odata.id": "/redfish/v1/ThermalEquipment/CDUs/1/LeakDetection"
}