{
    "@odata.type": "#MemoryChunks.v1_6_2.MemoryChunks",
    "Name": "Memory Chunk - Whole System",
    "Id": "1",
    "MemoryChunkSizeMiB": 32768,
    "AddressRangeType": "Volatile",
    "IsMirrorEnabled": false,
    "IsSpare": false,
    "InterleaveSets": [
        {
            "Memory": {
                "@odata.id": "/redfish/v1/Systems/2/Memory/1"
            }
        },
        {
            "Memory": {
                "@odata.id": "/redfish/v1/Systems/2/Memory/2"
            }
        },
        {
            "Memory": {
                "@odata.id": "/redfish/v1/Systems/2/Memory/3"
            }
        },
        {
            "Memory": {
                "@odata.id": "/redfish/v1/Systems/2/Memory/4"
            }
        }
    ],
    "@Redfish.Settings": {
        "@odata.type": "#Settings.v1_4_0.Settings",
        "SettingsObject": {
            "@odata.id": "/redfish/v1/Systems/2/MemoryDomains/1/MemoryChunks/1/SD"
        },
        "Time": "2012-03-07T14:44.30-05:00",
        "ETag": "someetag",
        "Messages": [
            {
                "MessageId": "Base.1.0.Success"
            }
        ]
    },
    "@odata.id": "/redfish/v1/Systems/2/MemoryDomains/1/MemoryChunks/1"
}