{
    "$ref": "#/definitions/BootOption",
    "$schema": "http://redfish.dmtf.org/schemas/v1/redfish-schema.v1_4_0.json",
    "copyright": "Copyright 2014-2018 Distributed Management Task Force, Inc. (DMTF). For the full DMTF copyright policy, see http://www.dmtf.org/about/policies/copyright",
    "definitions": {
        "BootOption": {
            "anyOf": [
                {
                    "$ref": "http://redfish.dmtf.org/schemas/v1/odata.v4_0_2.json#/definitions/idRef"
                },
                {
                    "$ref": "http://redfish.dmtf.org/schemas/v1/BootOption.v1_0_0.json#/definitions/BootOption"
                }
            ],
            "description": "The BootOption resource reports information about a single BootOption contained within a system."
        }
    },
    "owningEntity": "DMTF",
    "title": "#BootOption.BootOption"
}