{
    "@odata.type": "#MemoryChunksCollection.MemoryChunksCollection",
    "Name": "Memory Chunks Collection for PMEM Devices Domain",
    "Members@odata.count": 1,
    "Members": [
        {
            "@odata.id": "/redfish/v1/Systems/Config-4-PMEM/MemoryDomains/PMEM-1/MemoryChunks/PMEM-Persistent-5"
        }
    ],
    "@odata.id": "/redfish/v1/Systems/Config-4-PMEM/MemoryDomains/PMEM-1/MemoryChunks",
    "@Redfish.Copyright": "Copyright 2014-2025 DMTF. For the full DMTF copyright policy, see http://www.dmtf.org/about/policies/copyright."
}